clients/AkiraClient.py
clients/__init__.py
configuration/OptimusCloudConfiguration.py
configuration/__init__.py
driver/AndroidDriverFactory.py
driver/DriverCreatorFactory.py
driver/IosDriverFactory.py
driver/SessionManager.py
driver/__init__.py
entities/MandatoryCaps.py
entities/MobileDriverDetails.py
entities/SessionDetails.py
entities/SessionInfo.py
entities/SessionReservationDetails.py
entities/SessionState.py
entities/SessionsByPlatform.py
entities/__init__.py
exceptions/EmptySessionUrlException.py
exceptions/__init__.py
messaging/SessionConnection.py
messaging/SessionQueueReader.py
messaging/__init__.py
remote/OptimusCloudDriver.py
remote/OptimusCloudManager.py
remote/__init__.py
test/DriverFactory.py
test/TestPageTitle.py
test/__init__.py
test/test_PageTitle.py
test/test_PageTitle1.py
utils/BuildNoGenerator.py
utils/CapToManCapConverter.py
utils/CapabilitiesBuilder.py
utils/JsonUtil.py
utils/TestFeedToDesiredCapConverter.py
utils/__init__.py
Optimus_Python_Client-0.3.5.dist-info/LICENSE
Optimus_Python_Client-0.3.5.dist-info/METADATA
Optimus_Python_Client-0.3.5.dist-info/WHEEL
Optimus_Python_Client-0.3.5.dist-info/top_level.txt
Optimus_Python_Client-0.3.5.dist-info/RECORD
