Metadata-Version: 2.1
Name: Optimus-Python-Client
Version: 0.3.5
Summary: python-client for optimusCloud
Home-page: https://gitlab.com/testvagrant/optimus-pleiades/optimus-cloud/clients/python-client
Author: Nishant Sharma
Author-email: thenishant3@gmail.com
License: UNKNOWN
Platform: UNKNOWN
Classifier: Programming Language :: Python :: 3
Classifier: License :: OSI Approved :: MIT License
Classifier: Operating System :: OS Independent
Requires-Python: >=3.6
Requires-Dist: polling
Requires-Dist: retrying
Requires-Dist: requests
Requires-Dist: pika
Requires-Dist: atomos
Requires-Dist: selenium
Requires-Dist: Appium-Python-Client
